basecone/__init__.py
basecone/cli.py
basecone/client.py
basecone/model/__init__.py
basecone/model/artifact.py
basecone/model/company.py
basecone/model/document/__init__.py
basecone/model/document/company.py
basecone/model/document/tag.py
basecone/model/generalledger.py
basecone/model/transaction/__init__.py
basecone/server.py
basecone/utils.py
pyproject.toml
basecone-0.1.11.dist-info/entry_points.txt
basecone-0.1.11.dist-info/WHEEL
basecone-0.1.11.dist-info/METADATA
basecone-0.1.11.dist-info/RECORD
