Metadata-Version: 2.1
Name: basecone
Version: 0.1.11
Summary: 
Author: Pascal Prins
Author-email: pascal.prins@foobar-it.com
Requires-Python: >=3.7,<4.0
Classifier: Programming Language :: Python :: 3
Classifier: Programming Language :: Python :: 3.7
Classifier: Programming Language :: Python :: 3.8
Classifier: Programming Language :: Python :: 3.9
Requires-Dist: click (>=7.0,<8.0)
Requires-Dist: flask (>=1.1.2,<2.0.0)
Requires-Dist: pyyaml (>=5.3,<6.0)
Requires-Dist: requests (>=2.23.0,<3.0.0)
Requires-Dist: toml (>=0.10.1,<0.11.0)
